tests/__init__.py
tests/test_api.py
topgreenerapi/__init__.py
topgreenerapi/api.py
topgreenerapi/capability.py
topgreenerapi/device.py
topgreenerapi/device_type.py
topgreenerapi/exceptions.py
topgreenerapi/logger.py
topgreenerapi/util.py
topgreenerapi/models/__init__.py
topgreenerapi/models/device_schema.py
topgreenerapi/models/location.py
topgreenerapi/models/meta_schema.py
topgreenerapi/models/tuya_device.py
TopgreenerApi-0.8.7.dist-info/METADATA
TopgreenerApi-0.8.7.dist-info/WHEEL
TopgreenerApi-0.8.7.dist-info/top_level.txt
TopgreenerApi-0.8.7.dist-info/RECORD
