Metadata-Version: 2.1
Name: TopgreenerApi
Version: 0.8.7
Summary: Library for using Topgreener devices from Python
Home-page: UNKNOWN
Author: Raphael Budd
License: UNKNOWN
Platform: UNKNOWN
Classifier: Programming Language :: Python :: 3
Classifier: License :: OSI Approved :: MIT License
Classifier: Operating System :: OS Independent
Requires-Python: >=3.6
Requires-Dist: aiohttp
Requires-Dist: StrEnum
